color_change_filter.py
color_change_filter-1.1.5.dist-info/METADATA
color_change_filter-1.1.5.dist-info/WHEEL
color_change_filter-1.1.5.dist-info/entry_points.txt
color_change_filter-1.1.5.dist-info/top_level.txt
color_change_filter-1.1.5.dist-info/RECORD
