Metadata-Version: 2.1
Name: color_change_filter
Version: 1.1.5
Summary: Change color of image
Home-page: https://github.com/senbonmatsu/color_changer
Author: Chihiro senbonmatsu
Author-email: s2222020@stu.musahino-u.ac.jp
Project-URL: Bug Tracker, https://github.com/senbonmatsu/color_changer
Classifier: Programming Language :: Python :: 3
Classifier: License :: OSI Approved :: MIT License
Classifier: Operating System :: OS Independent
Requires-Dist: opencv-python
Requires-Dist: numpy
